oursolvers/__init__.py
oursolvers/wcvxopt.py
tests/__init__.py
tests/test_cvxopt_ilp.py
utils/__init__.py
utils/redirector.py
oursolvers-0.0.2.dist-info/LICENSE
oursolvers-0.0.2.dist-info/METADATA
oursolvers-0.0.2.dist-info/WHEEL
oursolvers-0.0.2.dist-info/top_level.txt
oursolvers-0.0.2.dist-info/RECORD
